ftsynthesis/DirectedAcyclicGraph.py
ftsynthesis/DistanceMatrix.py
ftsynthesis/SABRE_utility.py
ftsynthesis/__init__.py
ftsynthesis/checkup.py
ftsynthesis/depth_analysis.py
ftsynthesis/error.py
ftsynthesis/formatconversion.py
ftsynthesis/ftsynthesis.py
ftsynthesis/globalVariable.py
ftsynthesis/info.py
ftsynthesis/postprocess.py
ftsynthesis/util.py
tests/__init__.py
tests/layout_generator.py
tests/test.py
tests/util.py
ftsynthesis-0.0.2.dist-info/METADATA
ftsynthesis-0.0.2.dist-info/NOTICE.md
ftsynthesis-0.0.2.dist-info/WHEEL
ftsynthesis-0.0.2.dist-info/top_level.txt
ftsynthesis-0.0.2.dist-info/RECORD
